ridge_detection/__init__.py
ridge_detection/basicGeometry.py
ridge_detection/convol.py
ridge_detection/correct.py
ridge_detection/gui.py
ridge_detection/gui_helper.py
ridge_detection/helper.py
ridge_detection/lineDetector.py
ridge_detection/linesUtil.py
ridge_detection/link.py
ridge_detection/main.py
ridge_detection/params.py
ridge_detection/position.py
ridge_detection/run.py
ridge_detection/slopeOverlapResolver.py
ridge_detection/width.py
ridge_detection-3.0.0.dist-info/LICENSE.txt
ridge_detection-3.0.0.dist-info/METADATA
ridge_detection-3.0.0.dist-info/WHEEL
ridge_detection-3.0.0.dist-info/top_level.txt
ridge_detection-3.0.0.dist-info/RECORD
