Metadata-Version: 2.1
Name: ridge-detection
Version: 3.0.0
Summary: ridge / line detection algorithm 
Home-page: UNKNOWN
Author: Luca Lusnig
Author-email: luca.lusnig@mpi-dortmund.mpg.de
License: MIT
Platform: UNKNOWN
Classifier: Programming Language :: Python :: 3
Classifier: License :: OSI Approved :: MIT License
Classifier: Operating System :: OS Independent
Requires-Python: >3.4.0
Requires-Dist: numpy (>=1.14.0)
Requires-Dist: simplejson (>=3.16.0)
Requires-Dist: pillow (>=6.1.0)
Requires-Dist: mrcfile (>=1.1.2)
